fecho/__init__.py
fecho/cli.py
fecho/client.py
fecho/exceptions.py
fecho/utils.py
fecho-1.0.6.dist-info/LICENSE
fecho-1.0.6.dist-info/METADATA
fecho-1.0.6.dist-info/WHEEL
fecho-1.0.6.dist-info/entry_points.txt
fecho-1.0.6.dist-info/top_level.txt
fecho-1.0.6.dist-info/RECORD
